wilderness/__init__.py
wilderness/__version__.py
wilderness/application.py
wilderness/argparse_wrappers.py
wilderness/command.py
wilderness/documentable.py
wilderness/formatter.py
wilderness/group.py
wilderness/help.py
wilderness/manpages.py
wilderness/py.typed
wilderness/tester.py
wilderness-0.1.10.dist-info/LICENSE
wilderness-0.1.10.dist-info/METADATA
wilderness-0.1.10.dist-info/WHEEL
wilderness-0.1.10.dist-info/top_level.txt
wilderness-0.1.10.dist-info/RECORD
