Metadata-Version: 2.1
Name: wilderness
Version: 0.1.10
Summary: Easy multi-level command line applications with man pages
Home-page: https://github.com/GjjvdBurg/wilderness
Author: Gertjan van den Burg
Author-email: gertjanvandenburg@gmail.com
License: MIT
Classifier: License :: OSI Approved :: MIT License
Classifier: Programming Language :: Python
Classifier: Programming Language :: Python :: 3
Classifier: Programming Language :: Python :: 3.6
Classifier: Programming Language :: Python :: Implementation :: CPython
Classifier: Programming Language :: Python :: Implementation :: PyPy
Requires-Python: >=3.6.0
License-File: LICENSE
Provides-Extra: dev
Requires-Dist: sphinx ; extra == 'dev'
Requires-Dist: sphinx-rtd-theme ; extra == 'dev'
Requires-Dist: m2r2 ; extra == 'dev'
Requires-Dist: green ; extra == 'dev'
Requires-Dist: mypy ; extra == 'dev'
Requires-Dist: pytest (>=2.6) ; extra == 'dev'
Provides-Extra: docs
Requires-Dist: sphinx ; extra == 'docs'
Requires-Dist: sphinx-rtd-theme ; extra == 'docs'
Requires-Dist: m2r2 ; extra == 'docs'
Provides-Extra: tests
Requires-Dist: green ; extra == 'tests'
Requires-Dist: mypy ; extra == 'tests'
